LICENSE
README.rst
setup.py
cloudlanguagetools/__init__.py
cloudlanguagetools/alibaba.py
cloudlanguagetools/amazon.py
cloudlanguagetools/argostranslate.py
cloudlanguagetools/audio_processing.py
cloudlanguagetools/azure.py
cloudlanguagetools/cereproc.py
cloudlanguagetools/chatapi.py
cloudlanguagetools/constants.py
cloudlanguagetools/deepl.py
cloudlanguagetools/dictionarylookup.py
cloudlanguagetools/easypronunciation.py
cloudlanguagetools/elevenlabs.py
cloudlanguagetools/encryption.py
cloudlanguagetools/epitran.py
cloudlanguagetools/errors.py
cloudlanguagetools/forvo.py
cloudlanguagetools/fptai.py
cloudlanguagetools/gemini.py
cloudlanguagetools/google.py
cloudlanguagetools/keys.py
cloudlanguagetools/languages.py
cloudlanguagetools/libretranslate.py
cloudlanguagetools/mandarincantonese.py
cloudlanguagetools/naver.py
cloudlanguagetools/openai.py
cloudlanguagetools/options.py
cloudlanguagetools/pythainlp.py
cloudlanguagetools/service.py
cloudlanguagetools/servicemanager.py
cloudlanguagetools/spacy.py
cloudlanguagetools/test_services.py
cloudlanguagetools/tokenization.py
cloudlanguagetools/translationlanguage.py
cloudlanguagetools/transliterationlanguage.py
cloudlanguagetools/ttsvoice.py
cloudlanguagetools/vocalware.py
cloudlanguagetools/voicen.py
cloudlanguagetools/watson.py
cloudlanguagetools/wenlin.py
cloudlanguagetools.egg-info/PKG-INFO
cloudlanguagetools.egg-info/SOURCES.txt
cloudlanguagetools.egg-info/dependency_links.txt
cloudlanguagetools.egg-info/requires.txt
cloudlanguagetools.egg-info/top_level.txt
tests/test_audio.py
tests/test_breakdown.py
tests/test_chatapi.py
tests/test_dictionary_lookup.py
tests/test_llm.py
tests/test_mock_services.py
tests/test_servicemanager.py
tests/test_translation.py