Metadata-Version: 2.4
Name: cloudlanguagetools
Version: 14.3.5
Summary: Interface with various cloud APIs for language processing such as translation, text to speech
Home-page: https://github.com/Vocab-Apps/cloud-language-tools-core
Author: Luc
Author-email: languagetools@mailc.net
License: GPL
Classifier: Programming Language :: Python :: 3.12
Classifier: Topic :: Text Processing :: Linguistic
License-File: LICENSE
Requires-Dist: clt_requirements>=2.2
Dynamic: author
Dynamic: author-email
Dynamic: classifier
Dynamic: description
Dynamic: home-page
Dynamic: license
Dynamic: license-file
Dynamic: requires-dist
Dynamic: summary
